aws_access_key_id/__init__.py
aws_access_key_id-1.2.dist-info/licenses/LICENSE
aws_access_key_id-1.2.dist-info/METADATA
aws_access_key_id-1.2.dist-info/WHEEL
aws_access_key_id-1.2.dist-info/top_level.txt
aws_access_key_id-1.2.dist-info/RECORD
