Metadata-Version: 2.4
Name: aws_access_key_id
Version: 1.2
Summary: Extract AWS account ID and resource type from an AWS access key ID.
Home-page: https://github.com/nagwww/aws_access_key_id
Author: Nag Medida
Author-email: nagwww@gmail.com
Classifier: Programming Language :: Python :: 3
Classifier: License :: OSI Approved :: MIT License
Classifier: Operating System :: OS Independent
Requires-Python: >=3.6
License-File: LICENSE
Dynamic: author
Dynamic: author-email
Dynamic: classifier
Dynamic: description
Dynamic: description-content-type
Dynamic: home-page
Dynamic: license-file
Dynamic: requires-python
Dynamic: summary
